django_query_profiler/__init__.py
django_query_profiler/admin.py
django_query_profiler/middleware.py
django_query_profiler/models.py
django_query_profiler_Georgia-0.1.0.dist-info/METADATA
django_query_profiler_Georgia-0.1.0.dist-info/WHEEL
django_query_profiler_Georgia-0.1.0.dist-info/top_level.txt
django_query_profiler_Georgia-0.1.0.dist-info/RECORD
