Metadata-Version: 2.1
Name: django-query-profiler-Georgia
Version: 0.1.0
Summary: A utility to profile SQL queries made by Django ORM and provide insights into their performance
Home-page: https://github.com/APolevanov/django-admin-filters
Author: Anton Polevanov
Author-email: alulimmerkar@gmail.com
License: MIT License
Classifier: Development Status :: 3 - Alpha
Classifier: Intended Audience :: Developers
Classifier: License :: OSI Approved :: MIT License
Classifier: Operating System :: OS Independent
Classifier: Framework :: Django
Classifier: Programming Language :: Python
Classifier: Programming Language :: Python :: 3
Classifier: Programming Language :: Python :: 3.6
Classifier: Programming Language :: Python :: 3.7
Classifier: Programming Language :: Python :: 3.8
Classifier: Programming Language :: Python :: 3.9
Requires-Dist: Django (>=2.2)
